{"type":"FeatureCollection","features":[{"type":"Feature","properties":{"Name":"Covent Garden Market"},"geometry":{"type":"Point","coordinates":[-0.1242828369140625,51.51344322994464]}},{"type":"Feature","properties":{"Name":"Victoria Coach Station"},"geometry":{"type":"Point","coordinates":[-0.14350891113281247,51.49613345052725]}},{"type":"Feature","properties":{"Name":"Eastenders Queen Victoria Public House"},"geometry":{"type":"Point","coordinates":[-0.0913238525390625,51.49089648122356]}}]}
